cz_convnetional_ticket.py
convnetional_ticket-1.1.0.dist-info/METADATA
convnetional_ticket-1.1.0.dist-info/WHEEL
convnetional_ticket-1.1.0.dist-info/top_level.txt
convnetional_ticket-1.1.0.dist-info/RECORD
