Metadata-Version: 2.1
Name: convnetional-ticket
Version: 1.1.0
Summary: Conventional commits with tickets in changelog
Home-page: https://pypi.org/project/convnetional-ticket/
Author: Gohar Anwar
Author-email: gohar@goharanwar.com
License: MIT
Platform: UNKNOWN
Requires-Dist: commitizen
